pytest_dynamic_parameterize/__init__.py
pytest_dynamic_parameterize/const.py
pytest_dynamic_parameterize/dynamic_parameterize.py
pytest_dynamic_parameterize-1.0.3.dist-info/licenses/LICENSE
pytest_dynamic_parameterize-1.0.3.dist-info/METADATA
pytest_dynamic_parameterize-1.0.3.dist-info/WHEEL
pytest_dynamic_parameterize-1.0.3.dist-info/entry_points.txt
pytest_dynamic_parameterize-1.0.3.dist-info/top_level.txt
pytest_dynamic_parameterize-1.0.3.dist-info/RECORD
