Metadata-Version: 2.4
Name: pytest-dynamic-parameterize
Version: 1.0.3
Summary: A pytest plugin to dynamically parameterize tests based on external data sources.
Author: Avi Zaguri
License: MIT
Project-URL: Homepage, https://github.com/aviz92/pytest-dynamic-parameterize
Project-URL: Repository, https://github.com/aviz92/pytest-dynamic-parameterize
Project-URL: Issues, https://github.com/aviz92/pytest-dynamic-parameterize/issues
Keywords: development,pytest,plugin,testing,automation,dynamic,parameterize
Classifier: Development Status :: 5 - Production/Stable
Classifier: Intended Audience :: Developers
Classifier: Framework :: Pytest
Classifier: Programming Language :: Python :: 3.11
Classifier: Operating System :: OS Independent
Requires-Python: >=3.11
License-File: LICENSE
Requires-Dist: colorlog>=6.10.1
Requires-Dist: custom-python-logger>=2.0.10
Requires-Dist: pre-commit>=4.5.0
Requires-Dist: pytest>=9.0.1
Requires-Dist: python-dotenv>=1.2.1
Requires-Dist: setuptools>=80.9.0
Requires-Dist: wheel>=0.45.1
Dynamic: license-file
